<?xml version="1.0" encoding="UTF-8"?>
<objects serializationModel="Studio.02.02.00">
	<object class="AudioFile" id="{39208ba9-ade0-4123-9995-7e2d82c09f03}">
		<property name="assetPath">
			<value>piou_piou_mother_chicken.wav</value>
		</property>
		<property name="frequencyInKHz">
			<value>44.0999985</value>
		</property>
		<property name="channelCount">
			<value>2</value>
		</property>
		<property name="length">
			<value>1.2003854875283446</value>
		</property>
		<relationship name="masterAssetFolder">
			<destination>{8c8df525-65de-4fc6-a67f-e06370b5b35a}</destination>
		</relationship>
	</object>
</objects>
